gammarers/aws_ecs_fargate_task_termination_detection_event_rule/__init__.py
gammarers/aws_ecs_fargate_task_termination_detection_event_rule/py.typed
gammarers/aws_ecs_fargate_task_termination_detection_event_rule/_jsii/__init__.py
gammarers/aws_ecs_fargate_task_termination_detection_event_rule/_jsii/aws-ecs-fargate-task-termination-detection-event-rule@2.1.8.jsii.tgz
gammarers_aws_ecs_fargate_task_termination_detection_event_rule-2.1.8.dist-info/LICENSE
gammarers_aws_ecs_fargate_task_termination_detection_event_rule-2.1.8.dist-info/METADATA
gammarers_aws_ecs_fargate_task_termination_detection_event_rule-2.1.8.dist-info/WHEEL
gammarers_aws_ecs_fargate_task_termination_detection_event_rule-2.1.8.dist-info/top_level.txt
gammarers_aws_ecs_fargate_task_termination_detection_event_rule-2.1.8.dist-info/RECORD
