Metadata-Version: 2.1
Name: gammarers.aws-ecs-fargate-task-termination-detection-event-rule
Version: 2.1.8
Summary: This an AWS ECS Fargate task termination detection Event Rule.
Home-page: https://github.com/gammarers/aws-ecs-fargate-task-termination-detection-event-rule.git
Author: yicr<yicr@users.noreply.github.com>
License: Apache-2.0
Project-URL: Source, https://github.com/gammarers/aws-ecs-fargate-task-termination-detection-event-rule.git
Classifier: Intended Audience :: Developers
Classifier: Operating System :: OS Independent
Classifier: Programming Language :: JavaScript
Classifier: Programming Language :: Python :: 3 :: Only
Classifier: Programming Language :: Python :: 3.9
Classifier: Programming Language :: Python :: 3.10
Classifier: Programming Language :: Python :: 3.11
Classifier: Typing :: Typed
Classifier: Development Status :: 5 - Production/Stable
Classifier: License :: OSI Approved
Requires-Python: ~=3.9
License-File: LICENSE
Requires-Dist: aws-cdk-lib <3.0.0,>=2.189.1
Requires-Dist: constructs <11.0.0,>=10.0.5
Requires-Dist: gammarers.aws-cdk-errors <2.0.0,>=1.2.0
Requires-Dist: jsii <2.0.0,>=1.125.0
Requires-Dist: publication >=0.0.3
Requires-Dist: typeguard ==2.13.3
